[
  {
    "title": "تعداد بازدید وب‌سایت‌ها",
    "value": 1091550,
    "growth": 10,
    "chartData": [
      {
        "day": "شنبه",
        "visits": 144684
      },
      {
        "day": "یک‌شنبه",
        "visits": 157534
      },
      {
        "day": "دوشنبه",
        "visits": 139814
      },
      {
        "day": "سه‌شنبه",
        "visits": 147924
      },
      {
        "day": "چهارشنبه",
        "visits": 155284
      },
      {
        "day": "پنج‌شنبه",
        "visits": 168614
      },
      {
        "day": "جمعه",
        "visits": 136844
      }
    ]
  },
  {
    "title": "تعداد کاربران جدید",
    "value": 2143,
    "growth": 5,
    "chartData": [
      {
        "day": "شنبه",
        "visits": 2332
      },
      {
        "day": "یک‌شنبه",
        "visits": 2329
      },
      {
        "day": "دوشنبه",
        "visits": 2334
      },
      {
        "day": "سه‌شنبه",
        "visits": 2333
      },
      {
        "day": "چهارشنبه",
        "visits": 2336
      },
      {
        "day": "پنج‌شنبه",
        "visits": 2338
      },
      {
        "day": "جمعه",
        "visits": 2349
      }
    ]
  },
  {
    "title": "وب‌سایت‌های زیرمجموعه",
    "value": 2325,
    "growth": 3,
    "chartData": [
      {
        "day": "شنبه",
        "visits": 2352
      },
      {
        "day": "یک‌شنبه",
        "visits": 2359
      },
      {
        "day": "دوشنبه",
        "visits": 2367
      },
      {
        "day": "سه‌شنبه",
        "visits": 2361
      },
      {
        "day": "چهارشنبه",
        "visits": 2365
      },
      {
        "day": "پنج‌شنبه",
        "visits": 2368
      },
      {
        "day": "جمعه",
        "visits": 2361
      }
    ]
  },
  {
    "title": "سرورهای فعال",
    "value": 2543,
    "growth": 2,
    "chartData": [
      {
        "day": "شنبه",
        "visits": 2334
      },
      {
        "day": "یک‌شنبه",
        "visits": 2345
      },
      {
        "day": "دوشنبه",
        "visits": 2341
      },
      {
        "day": "سه‌شنبه",
        "visits": 2333
      },
      {
        "day": "چهارشنبه",
        "visits": 2349
      },
      {
        "day": "پنج‌شنبه",
        "visits": 2326
      },
      {
        "day": "جمعه",
        "visits": 2323
      }
    ]
  },
  {
    "title": "تحلیل‌های امروز",
    "value": 2037,
    "growth": 4,
    "chartData": [
      {
        "day": "شنبه",
        "visits": 2319
      },
      {
        "day": "یک‌شنبه",
        "visits": 2320
      },
      {
        "day": "دوشنبه",
        "visits": 2321
      },
      {
        "day": "سه‌شنبه",
        "visits": 2321
      },
      {
        "day": "چهارشنبه",
        "visits": 2322
      },
      {
        "day": "پنج‌شنبه",
        "visits": 2321
      },
      {
        "day": "جمعه",
        "visits": 2321
      }
    ]
  },
  {
    "title": "قطع همکاری‌های هفته اخیر",
    "value": 2051,
    "growth": -9,
    "chartData": [
      {
        "day": "شنبه",
        "visits": 2321
      },
      {
        "day": "یک‌شنبه",
        "visits": 2324
      },
      {
        "day": "دوشنبه",
        "visits": 2323
      },
      {
        "day": "سه‌شنبه",
        "visits": 2325
      },
      {
        "day": "چهارشنبه",
        "visits": 2322
      },
      {
        "day": "پنج‌شنبه",
        "visits": 2321
      },
      {
        "day": "جمعه",
        "visits": 2323
      }
    ]
  }
]