[
  {
    "title": "تعداد بازدید وب‌سایت‌ها",
    "value": 1090110,
    "growth": 10,
    "chartData": [
      {
        "day": "شنبه",
        "visits": 142956
      },
      {
        "day": "یک‌شنبه",
        "visits": 155806
      },
      {
        "day": "دوشنبه",
        "visits": 138086
      },
      {
        "day": "سه‌شنبه",
        "visits": 146196
      },
      {
        "day": "چهارشنبه",
        "visits": 153556
      },
      {
        "day": "پنج‌شنبه",
        "visits": 166886
      },
      {
        "day": "جمعه",
        "visits": 135116
      }
    ]
  },
  {
    "title": "تعداد کاربران جدید",
    "value": 703,
    "growth": 5,
    "chartData": [
      {
        "day": "شنبه",
        "visits": 604
      },
      {
        "day": "یک‌شنبه",
        "visits": 601
      },
      {
        "day": "دوشنبه",
        "visits": 606
      },
      {
        "day": "سه‌شنبه",
        "visits": 605
      },
      {
        "day": "چهارشنبه",
        "visits": 608
      },
      {
        "day": "پنج‌شنبه",
        "visits": 610
      },
      {
        "day": "جمعه",
        "visits": 621
      }
    ]
  },
  {
    "title": "وب‌سایت‌های زیرمجموعه",
    "value": 885,
    "growth": 3,
    "chartData": [
      {
        "day": "شنبه",
        "visits": 624
      },
      {
        "day": "یک‌شنبه",
        "visits": 631
      },
      {
        "day": "دوشنبه",
        "visits": 639
      },
      {
        "day": "سه‌شنبه",
        "visits": 633
      },
      {
        "day": "چهارشنبه",
        "visits": 637
      },
      {
        "day": "پنج‌شنبه",
        "visits": 640
      },
      {
        "day": "جمعه",
        "visits": 633
      }
    ]
  },
  {
    "title": "سرورهای فعال",
    "value": 1103,
    "growth": 2,
    "chartData": [
      {
        "day": "شنبه",
        "visits": 606
      },
      {
        "day": "یک‌شنبه",
        "visits": 617
      },
      {
        "day": "دوشنبه",
        "visits": 613
      },
      {
        "day": "سه‌شنبه",
        "visits": 605
      },
      {
        "day": "چهارشنبه",
        "visits": 621
      },
      {
        "day": "پنج‌شنبه",
        "visits": 598
      },
      {
        "day": "جمعه",
        "visits": 595
      }
    ]
  },
  {
    "title": "تحلیل‌های امروز",
    "value": 597,
    "growth": 4,
    "chartData": [
      {
        "day": "شنبه",
        "visits": 591
      },
      {
        "day": "یک‌شنبه",
        "visits": 592
      },
      {
        "day": "دوشنبه",
        "visits": 593
      },
      {
        "day": "سه‌شنبه",
        "visits": 593
      },
      {
        "day": "چهارشنبه",
        "visits": 594
      },
      {
        "day": "پنج‌شنبه",
        "visits": 593
      },
      {
        "day": "جمعه",
        "visits": 593
      }
    ]
  },
  {
    "title": "قطع همکاری‌های هفته اخیر",
    "value": 611,
    "growth": -9,
    "chartData": [
      {
        "day": "شنبه",
        "visits": 593
      },
      {
        "day": "یک‌شنبه",
        "visits": 596
      },
      {
        "day": "دوشنبه",
        "visits": 595
      },
      {
        "day": "سه‌شنبه",
        "visits": 597
      },
      {
        "day": "چهارشنبه",
        "visits": 594
      },
      {
        "day": "پنج‌شنبه",
        "visits": 593
      },
      {
        "day": "جمعه",
        "visits": 595
      }
    ]
  }
]