[
  {
    "title": "تعداد بازدید وب‌سایت‌ها",
    "value": 1092040,
    "growth": 10,
    "chartData": [
      {
        "day": "شنبه",
        "visits": 145272
      },
      {
        "day": "یک‌شنبه",
        "visits": 158122
      },
      {
        "day": "دوشنبه",
        "visits": 140402
      },
      {
        "day": "سه‌شنبه",
        "visits": 148512
      },
      {
        "day": "چهارشنبه",
        "visits": 155872
      },
      {
        "day": "پنج‌شنبه",
        "visits": 169202
      },
      {
        "day": "جمعه",
        "visits": 137432
      }
    ]
  },
  {
    "title": "تعداد کاربران جدید",
    "value": 2633,
    "growth": 5,
    "chartData": [
      {
        "day": "شنبه",
        "visits": 2920
      },
      {
        "day": "یک‌شنبه",
        "visits": 2917
      },
      {
        "day": "دوشنبه",
        "visits": 2922
      },
      {
        "day": "سه‌شنبه",
        "visits": 2921
      },
      {
        "day": "چهارشنبه",
        "visits": 2924
      },
      {
        "day": "پنج‌شنبه",
        "visits": 2926
      },
      {
        "day": "جمعه",
        "visits": 2937
      }
    ]
  },
  {
    "title": "وب‌سایت‌های زیرمجموعه",
    "value": 2815,
    "growth": 3,
    "chartData": [
      {
        "day": "شنبه",
        "visits": 2940
      },
      {
        "day": "یک‌شنبه",
        "visits": 2947
      },
      {
        "day": "دوشنبه",
        "visits": 2955
      },
      {
        "day": "سه‌شنبه",
        "visits": 2949
      },
      {
        "day": "چهارشنبه",
        "visits": 2953
      },
      {
        "day": "پنج‌شنبه",
        "visits": 2956
      },
      {
        "day": "جمعه",
        "visits": 2949
      }
    ]
  },
  {
    "title": "سرورهای فعال",
    "value": 3033,
    "growth": 2,
    "chartData": [
      {
        "day": "شنبه",
        "visits": 2922
      },
      {
        "day": "یک‌شنبه",
        "visits": 2933
      },
      {
        "day": "دوشنبه",
        "visits": 2929
      },
      {
        "day": "سه‌شنبه",
        "visits": 2921
      },
      {
        "day": "چهارشنبه",
        "visits": 2937
      },
      {
        "day": "پنج‌شنبه",
        "visits": 2914
      },
      {
        "day": "جمعه",
        "visits": 2911
      }
    ]
  },
  {
    "title": "تحلیل‌های امروز",
    "value": 2527,
    "growth": 4,
    "chartData": [
      {
        "day": "شنبه",
        "visits": 2907
      },
      {
        "day": "یک‌شنبه",
        "visits": 2908
      },
      {
        "day": "دوشنبه",
        "visits": 2909
      },
      {
        "day": "سه‌شنبه",
        "visits": 2909
      },
      {
        "day": "چهارشنبه",
        "visits": 2910
      },
      {
        "day": "پنج‌شنبه",
        "visits": 2909
      },
      {
        "day": "جمعه",
        "visits": 2909
      }
    ]
  },
  {
    "title": "قطع همکاری‌های هفته اخیر",
    "value": 2541,
    "growth": -9,
    "chartData": [
      {
        "day": "شنبه",
        "visits": 2909
      },
      {
        "day": "یک‌شنبه",
        "visits": 2912
      },
      {
        "day": "دوشنبه",
        "visits": 2911
      },
      {
        "day": "سه‌شنبه",
        "visits": 2913
      },
      {
        "day": "چهارشنبه",
        "visits": 2910
      },
      {
        "day": "پنج‌شنبه",
        "visits": 2909
      },
      {
        "day": "جمعه",
        "visits": 2911
      }
    ]
  }
]